{"nodes": [{"id": "augmentation_augment_train", "label": "augment_train(train_df, strategy, n_augmented, noise_sigma, scaling_range, seed)", "file_type": "code", "source_file": "src/phm/augmentation.py", "source_location": "line 97", "source_url": null, "captured_at": null, "author": null, "contributor": null}, {"id": "augmentation_feature_noise", "label": "_augment_feature_noise (Gaussian noise relative to std)", "file_type": "code", "source_file": "src/phm/augmentation.py", "source_location": "line 55", "source_url": null, "captured_at": null, "author": null, "contributor": null}, {"id": "augmentation_feature_scaling", "label": "_augment_feature_scaling (uniform multiplier per feature)", "file_type": "code", "source_file": "src/phm/augmentation.py", "source_location": "line 65", "source_url": null, "captured_at": null, "author": null, "contributor": null}, {"id": "augmentation_grouped_scaling", "label": "_augment_grouped_scaling (same factor per {A|R}_p{n} group)", "file_type": "code", "source_file": "src/phm/augmentation.py", "source_location": "line 75", "source_url": null, "captured_at": null, "author": null, "contributor": null}, {"id": "augmentation_clip_physical", "label": "_clip_physical (non-negative constraint for physical features)", "file_type": "code", "source_file": "src/phm/augmentation.py", "source_location": "line 44", "source_url": null, "captured_at": null, "author": null, "contributor": null}, {"id": "augmentation_feature_cols", "label": "_feature_cols (numeric non-protected columns)", "file_type": "code", "source_file": "src/phm/augmentation.py", "source_location": "line 32", "source_url": null, "captured_at": null, "author": null, "contributor": null}, {"id": "augmentation_is_augmented_flag", "label": "is_augmented flag column", "file_type": "code", "source_file": "src/phm/augmentation.py", "source_location": "line 111", "source_url": null, "captured_at": null, "author": null, "contributor": null}, {"id": "augmentation_GROUP_RE", "label": "_GROUP_RE = r'^([AR]_p\\d+)_' (group regex)", "file_type": "code", "source_file": "src/phm/augmentation.py", "source_location": "line 29", "source_url": null, "captured_at": null, "author": null, "contributor": null}], "edges": [{"source": "augmentation_augment_train", "target": "config_AUGMENTATION_PROTECTED_COLS", "relation": "references", "confidence": "EXTRACTED", "confidence_score": 1.0, "source_file": "src/phm/augmentation.py", "source_location": "line 22", "weight": 1.0}, {"source": "augmentation_augment_train", "target": "config_AUGMENTATION_NOISE_SIGMA", "relation": "references", "confidence": "EXTRACTED", "confidence_score": 1.0, "source_file": "src/phm/augmentation.py", "source_location": "line 22", "weight": 1.0}, {"source": "augmentation_augment_train", "target": "config_AUGMENTATION_SCALING_RANGE", "relation": "references", "confidence": "EXTRACTED", "confidence_score": 1.0, "source_file": "src/phm/augmentation.py", "source_location": "line 22", "weight": 1.0}, {"source": "augmentation_augment_train", "target": "config_N_AUGMENTED_PER_EXPERIMENT", "relation": "references", "confidence": "EXTRACTED", "confidence_score": 1.0, "source_file": "src/phm/augmentation.py", "source_location": "line 99", "weight": 1.0}, {"source": "augmentation_augment_train", "target": "augmentation_feature_noise", "relation": "calls", "confidence": "EXTRACTED", "confidence_score": 1.0, "source_file": "src/phm/augmentation.py", "source_location": "line 128", "weight": 1.0}, {"source": "augmentation_augment_train", "target": "augmentation_feature_scaling", "relation": "calls", "confidence": "EXTRACTED", "confidence_score": 1.0, "source_file": "src/phm/augmentation.py", "source_location": "line 130", "weight": 1.0}, {"source": "augmentation_augment_train", "target": "augmentation_grouped_scaling", "relation": "calls", "confidence": "EXTRACTED", "confidence_score": 1.0, "source_file": "src/phm/augmentation.py", "source_location": "line 132", "weight": 1.0}, {"source": "augmentation_augment_train", "target": "augmentation_clip_physical", "relation": "calls", "confidence": "EXTRACTED", "confidence_score": 1.0, "source_file": "src/phm/augmentation.py", "source_location": "line 136", "weight": 1.0}, {"source": "augmentation_augment_train", "target": "augmentation_is_augmented_flag", "relation": "references", "confidence": "EXTRACTED", "confidence_score": 1.0, "source_file": "src/phm/augmentation.py", "source_location": "line 137", "weight": 1.0}, {"source": "augmentation_augment_train", "target": "config_TARGET_COLUMN", "relation": "references", "confidence": "EXTRACTED", "confidence_score": 1.0, "source_file": "src/phm/augmentation.py", "source_location": "line 10", "weight": 1.0}, {"source": "augmentation_clip_physical", "target": "config_PHYSICAL_NONNEGATIVE_SUFFIXES", "relation": "references", "confidence": "EXTRACTED", "confidence_score": 1.0, "source_file": "src/phm/augmentation.py", "source_location": "line 46", "weight": 1.0}, {"source": "augmentation_grouped_scaling", "target": "augmentation_GROUP_RE", "relation": "references", "confidence": "EXTRACTED", "confidence_score": 1.0, "source_file": "src/phm/augmentation.py", "source_location": "line 81", "weight": 1.0}, {"source": "augmentation_augment_train", "target": "concept_VBum", "relation": "references", "confidence": "INFERRED", "confidence_score": 0.95, "source_file": "src/phm/augmentation.py", "source_location": "line 10", "weight": 1.0}, {"source": "augmentation_augment_train", "target": "concept_data_branch_A", "relation": "implements", "confidence": "INFERRED", "confidence_score": 0.95, "source_file": "src/phm/augmentation.py", "source_location": "line 97", "weight": 1.0}], "hyperedges": [{"id": "augmentation_strategies_set", "label": "Three augmentation strategies applied to training data only", "nodes": ["augmentation_feature_noise", "augmentation_feature_scaling", "augmentation_grouped_scaling", "augmentation_augment_train", "augmentation_is_augmented_flag", "config_AUGMENTATION_PROTECTED_COLS"], "relation": "implement", "confidence": "EXTRACTED", "confidence_score": 1.0, "source_file": "src/phm/augmentation.py"}]}