{"nodes": [{"id": "10_shap_bar_elasticnet_a_st_feature_noise", "label": "SHAP Bar Chart \u2014 ElasticNet A_ST_feature_noise (Best Global)", "file_type": "image", "source_file": "outputs/figures/shap/10_shap_bar_elasticnet_a_st_feature_noise.png", "source_location": null, "source_url": null, "captured_at": null, "author": null, "contributor": null}, {"id": "concept_shap_elasticnet_top5_a_st_fn", "label": "SHAP Top-5 Features ElasticNet A_ST_feature_noise: A_p1_skewness(2.19), A_rms_std_6_contacts(2.15), R_p1_crest_factor(1.95), R_rms_std_6_contacts(1.85), A_p1_crest_factor(1.57)", "file_type": "rationale", "source_file": "outputs/figures/shap/10_shap_bar_elasticnet_a_st_feature_noise.png", "source_location": null, "source_url": null, "captured_at": null, "author": null, "contributor": null}, {"id": "feature_A_p1_skewness", "label": "Feature: A_p1_skewness \u2014 Acoustic Signal Pass-1 Skewness (statistical moment)", "file_type": "rationale", "source_file": "outputs/figures/shap/10_shap_bar_elasticnet_a_st_feature_noise.png", "source_location": null, "source_url": null, "captured_at": null, "author": null, "contributor": null}, {"id": "feature_A_rms_std_6_contacts", "label": "Feature: A_rms_std_6_contacts \u2014 Std Dev of RMS over 6 Contacts (Acoustic)", "file_type": "rationale", "source_file": "outputs/figures/shap/10_shap_bar_elasticnet_a_st_feature_noise.png", "source_location": null, "source_url": null, "captured_at": null, "author": null, "contributor": null}, {"id": "feature_R_p1_crest_factor", "label": "Feature: R_p1_crest_factor \u2014 Raw Signal Pass-1 Crest Factor (peak/RMS ratio)", "file_type": "rationale", "source_file": "outputs/figures/shap/10_shap_bar_elasticnet_a_st_feature_noise.png", "source_location": null, "source_url": null, "captured_at": null, "author": null, "contributor": null}, {"id": "feature_R_rms_std_6_contacts", "label": "Feature: R_rms_std_6_contacts \u2014 Std Dev of RMS over 6 Contacts (Raw Signal)", "file_type": "rationale", "source_file": "outputs/figures/shap/10_shap_bar_elasticnet_a_st_feature_noise.png", "source_location": null, "source_url": null, "captured_at": null, "author": null, "contributor": null}, {"id": "feature_A_p1_crest_factor", "label": "Feature: A_p1_crest_factor \u2014 Acoustic Signal Pass-1 Crest Factor", "file_type": "rationale", "source_file": "outputs/figures/shap/10_shap_bar_elasticnet_a_st_feature_noise.png", "source_location": null, "source_url": null, "captured_at": null, "author": null, "contributor": null}, {"id": "feature_R_p4_dominant_freq_hz", "label": "Feature: R_p4_dominant_freq_hz \u2014 Raw Signal Pass-4 Dominant Frequency (Hz)", "file_type": "rationale", "source_file": "outputs/figures/shap/10_shap_bar_elasticnet_a_st_feature_noise.png", "source_location": null, "source_url": null, "captured_at": null, "author": null, "contributor": null}], "edges": [{"source": "10_shap_bar_elasticnet_a_st_feature_noise", "target": "concept_elasticnet_best_global", "relation": "references", "confidence": "EXTRACTED", "confidence_score": 1.0, "source_file": "outputs/figures/shap/10_shap_bar_elasticnet_a_st_feature_noise.png", "source_location": null, "weight": 1.0}, {"source": "10_shap_bar_elasticnet_a_st_feature_noise", "target": "concept_shap_elasticnet_top5_a_st_fn", "relation": "rationale_for", "confidence": "EXTRACTED", "confidence_score": 1.0, "source_file": "outputs/figures/shap/10_shap_bar_elasticnet_a_st_feature_noise.png", "source_location": null, "weight": 1.0}, {"source": "10_shap_bar_elasticnet_a_st_feature_noise", "target": "feature_A_p1_skewness", "relation": "references", "confidence": "EXTRACTED", "confidence_score": 1.0, "source_file": "outputs/figures/shap/10_shap_bar_elasticnet_a_st_feature_noise.png", "source_location": null, "weight": 1.0}, {"source": "10_shap_bar_elasticnet_a_st_feature_noise", "target": "feature_A_rms_std_6_contacts", "relation": "references", "confidence": "EXTRACTED", "confidence_score": 1.0, "source_file": "outputs/figures/shap/10_shap_bar_elasticnet_a_st_feature_noise.png", "source_location": null, "weight": 1.0}, {"source": "10_shap_bar_elasticnet_a_st_feature_noise", "target": "feature_R_p1_crest_factor", "relation": "references", "confidence": "EXTRACTED", "confidence_score": 1.0, "source_file": "outputs/figures/shap/10_shap_bar_elasticnet_a_st_feature_noise.png", "source_location": null, "weight": 1.0}, {"source": "10_shap_bar_elasticnet_a_st_feature_noise", "target": "feature_R_rms_std_6_contacts", "relation": "references", "confidence": "EXTRACTED", "confidence_score": 1.0, "source_file": "outputs/figures/shap/10_shap_bar_elasticnet_a_st_feature_noise.png", "source_location": null, "weight": 1.0}, {"source": "10_shap_bar_elasticnet_a_st_feature_noise", "target": "feature_A_p1_crest_factor", "relation": "references", "confidence": "EXTRACTED", "confidence_score": 1.0, "source_file": "outputs/figures/shap/10_shap_bar_elasticnet_a_st_feature_noise.png", "source_location": null, "weight": 1.0}, {"source": "concept_shap_elasticnet_top5_a_st_fn", "target": "concept_shap_elasticnet_top5_n_st", "relation": "semantically_similar_to", "confidence": "INFERRED", "confidence_score": 0.95, "source_file": "outputs/figures/shap/10_shap_bar_elasticnet_a_st_feature_noise.png", "source_location": null, "weight": 0.95}, {"source": "feature_A_p1_skewness", "target": "concept_shap_elasticnet_top5_a_st_fn", "relation": "conceptually_related_to", "confidence": "EXTRACTED", "confidence_score": 1.0, "source_file": "outputs/figures/shap/10_shap_bar_elasticnet_a_st_feature_noise.png", "source_location": null, "weight": 1.0}], "hyperedges": [{"id": "shap_elasticnet_interpretability_group", "label": "SHAP Interpretability for ElasticNet Models (N_ST and A_ST_feature_noise)", "nodes": ["10_shap_bar_elasticnet_a_st_feature_noise", "10_shap_bar_elasticnet_n_st", "10_shap_summary_elasticnet_a_st_feature_noise", "10_shap_summary_elasticnet_n_st", "concept_shap_elasticnet_consistent_features", "concept_shap_elasticnet_directions"], "relation": "participate_in", "confidence": "INFERRED", "confidence_score": 0.95, "source_file": "outputs/figures/shap/10_shap_bar_elasticnet_a_st_feature_noise.png"}, {"id": "shap_top_features_shared_acoustic", "label": "Top Shared Features Across ElasticNet Models: Acoustic Skewness, RMS Std, Crest Factor", "nodes": ["feature_A_p1_skewness", "feature_A_rms_std_6_contacts", "feature_R_p1_crest_factor", "feature_R_rms_std_6_contacts", "feature_A_p1_crest_factor", "concept_shap_elasticnet_consistent_features"], "relation": "form", "confidence": "EXTRACTED", "confidence_score": 1.0, "source_file": "outputs/figures/shap/10_shap_bar_elasticnet_a_st_feature_noise.png"}]}