{"nodes": [{"id": "run_full_pipeline_script", "label": "run_full_pipeline.py \u2014 Linear Pipeline Orchestrator", "file_type": "code", "source_file": "scripts/run_full_pipeline.py", "source_location": null, "source_url": null, "captured_at": null, "author": null, "contributor": null}], "edges": [{"source": "run_full_pipeline_script", "target": "audit_data_script", "relation": "calls", "confidence": "EXTRACTED", "confidence_score": 1.0, "source_file": "scripts/run_full_pipeline.py", "source_location": "STEPS list, Paso 0/6", "weight": 1.0}, {"source": "run_full_pipeline_script", "target": "build_dataset_script", "relation": "calls", "confidence": "EXTRACTED", "confidence_score": 1.0, "source_file": "scripts/run_full_pipeline.py", "source_location": "STEPS list, Paso 1/6", "weight": 1.0}, {"source": "run_full_pipeline_script", "target": "train_baselines_script", "relation": "calls", "confidence": "EXTRACTED", "confidence_score": 1.0, "source_file": "scripts/run_full_pipeline.py", "source_location": "STEPS list, Paso 2/6", "weight": 1.0}, {"source": "run_full_pipeline_script", "target": "run_tuning_script", "relation": "calls", "confidence": "EXTRACTED", "confidence_score": 1.0, "source_file": "scripts/run_full_pipeline.py", "source_location": "STEPS list, Paso 3/6", "weight": 1.0}, {"source": "run_full_pipeline_script", "target": "run_augmentation_script", "relation": "calls", "confidence": "EXTRACTED", "confidence_score": 1.0, "source_file": "scripts/run_full_pipeline.py", "source_location": "STEPS list, Paso 4/6", "weight": 1.0}, {"source": "run_full_pipeline_script", "target": "evaluate_models_script", "relation": "calls", "confidence": "EXTRACTED", "confidence_score": 1.0, "source_file": "scripts/run_full_pipeline.py", "source_location": "STEPS list, Paso 5/6", "weight": 1.0}, {"source": "run_full_pipeline_script", "target": "run_shap_script", "relation": "calls", "confidence": "EXTRACTED", "confidence_score": 1.0, "source_file": "scripts/run_full_pipeline.py", "source_location": "STEPS list, Paso 6/6", "weight": 1.0}], "hyperedges": [{"id": "linear_pipeline_sequence", "label": "Linear Pipeline: Steps 0-6 Executed by run_full_pipeline.py", "nodes": ["run_full_pipeline_script", "audit_data_script", "build_dataset_script", "train_baselines_script", "run_tuning_script", "run_augmentation_script", "evaluate_models_script", "run_shap_script"], "relation": "participate_in", "confidence": "EXTRACTED", "confidence_score": 1.0, "source_file": "scripts/run_full_pipeline.py"}]}